demo/__init__.py
demo/converter.py
demo_lt.v0.1-0.1.dist-info/METADATA
demo_lt.v0.1-0.1.dist-info/RECORD
demo_lt.v0.1-0.1.dist-info/WHEEL
demo_lt.v0.1-0.1.dist-info/entry_points.txt
demo_lt.v0.1-0.1.dist-info/top_level.txt
