Metadata-Version: 2.1
Name: demo-lt.v0.1
Version: 0.1
Summary: test
Home-page: UNKNOWN
Author: qingtian
Author-email: 
License: UNKNOWN
Platform: UNKNOWN
Classifier: Programming Language :: Python :: 3
Classifier: License :: OSI Approved :: MIT License
Classifier: Operating System :: OS Independent
Requires-Dist: numpy (==1.14.4)
